{"title":"百度_20141219_Deep Speech：Scaling up end-to-end speech recognition","slug":"Paper016","date":"2021-01-11T14:45:26.000Z","updated":"2021-01-11T14:53:54.000Z","comments":true,"path":"api/articles/Paper016.json","excerpt":null,"covers":null,"content":"<link rel=\"stylesheet\" class=\"aplayer-secondary-style-marker\" href=\"/assets/css/APlayer.min.css\"><script src=\"/assets/js/APlayer.min.js\" class=\"aplayer-secondary-script-marker\"></script><script class=\"meting-secondary-script-marker\" src=\"/assets/js/Meting.min.js\"></script><p><strong>摘要</strong><br>我们提出一个使用端到端深度学习开发的最先进的语音识别系统。我们的架构比传统的语音系统要简单得多，传统的语音系统依赖于费力的工程处理流程；当在嘈杂的环境中使用时，这些传统的系统也往往表现不佳。相比之下，我们的系统不需要手工设计的组件来模拟背景噪声、混响或扬声器变化，而是直接学习一个对这些影响具有鲁棒性的函数。相比之下，我们的系统不需要手工设计的组件来模拟背景噪声、混响或说话人变化，而是直接学习一个对这些影响具有鲁棒性的函数。我们不需要音素词典，甚至不需要“音素”的概念。该方法的关键是一个优化良好的RNN训练系统，使用多个gpu，以及一套新型的数据合成技术，使我们能够有效地获取大量不同的数据来进行训练。我们的系统称为DeepSpeech，在广泛研究的Switchboard Hub5’00数据集上优于以前发表的结果，在整个测试集实现了16.0%的错误率。与广泛使用的、最先进的商业语音系统相比，DeepSpeech还能更好地处理充满挑战的嘈杂环境。</p>\n<p><strong>参考</strong><br>[1] <em>Hannun A, Case C, Casper J, et al. Deep speech: Scaling up end-to-end speech recognition[J]. arXiv preprint arXiv:1412.5567, 2014.</em><a href=\"https://arxiv.org/abs/1412.5567\">[pdf]</a></p>\n","more":"<p><strong>摘要</strong><br>我们提出一个使用端到端深度学习开发的最先进的语音识别系统。我们的架构比传统的语音系统要简单得多，传统的语音系统依赖于费力的工程处理流程；当在嘈杂的环境中使用时，这些传统的系统也往往表现不佳。相比之下，我们的系统不需要手工设计的组件来模拟背景噪声、混响或扬声器变化，而是直接学习一个对这些影响具有鲁棒性的函数。相比之下，我们的系统不需要手工设计的组件来模拟背景噪声、混响或说话人变化，而是直接学习一个对这些影响具有鲁棒性的函数。我们不需要音素词典，甚至不需要“音素”的概念。该方法的关键是一个优化良好的RNN训练系统，使用多个gpu，以及一套新型的数据合成技术，使我们能够有效地获取大量不同的数据来进行训练。我们的系统称为DeepSpeech，在广泛研究的Switchboard Hub5’00数据集上优于以前发表的结果，在整个测试集实现了16.0%的错误率。与广泛使用的、最先进的商业语音系统相比，DeepSpeech还能更好地处理充满挑战的嘈杂环境。</p>\n<p><strong>参考</strong><br>[1] <em>Hannun A, Case C, Casper J, et al. Deep speech: Scaling up end-to-end speech recognition[J]. arXiv preprint arXiv:1412.5567, 2014.</em><a href=\"https://arxiv.org/abs/1412.5567\">[pdf]</a></p>\n","categories":[{"name":"Paper","path":"api/categories/Paper.json"}],"tags":[{"name":"语音识别","path":"api/tags/语音识别.json"},{"name":"语言模型","path":"api/tags/语言模型.json"},{"name":"End-to-End","path":"api/tags/End-to-End.json"},{"name":"声学模型","path":"api/tags/声学模型.json"},{"name":"解码器","path":"api/tags/解码器.json"},{"name":"CTC","path":"api/tags/CTC.json"},{"name":"RNN","path":"api/tags/RNN.json"},{"name":"N-Gram","path":"api/tags/N-Gram.json"}]}