{"title":"谷歌_ICASSP2018_Generalized End-to-End Loss for Speaker Verification","slug":"Paper027","date":"2021-01-27T15:02:39.000Z","updated":"2021-01-27T15:11:39.000Z","comments":true,"path":"api/articles/Paper027.json","excerpt":null,"covers":null,"content":"<link rel=\"stylesheet\" class=\"aplayer-secondary-style-marker\" href=\"/assets/css/APlayer.min.css\"><script src=\"/assets/js/APlayer.min.js\" class=\"aplayer-secondary-script-marker\"></script><script class=\"meting-secondary-script-marker\" src=\"/assets/js/Meting.min.js\"></script><p><strong>摘要</strong><br>本文提出了一种新型的损失函数，称为广义端到端（GE2E）损失函数，使得说话人认证模型的训练比以前基于元组的端到端（TE2E）损失函数更加有效。与TE2E不同，GE2E损失函数以强调实例的方式更新网络，这些实例在训练过程的每个步骤中都难以验证。此外，GE2E损失函数不需要选择示例的初始阶段。利用这些特性，我们的新损失函数模型使说话人验证EER降低了10%以上，同时使训练时间减少了60%。从而学习出一个更好的模型。我们还介绍了MultiReader技术，它允许我们进行域自适应训练一个更精确的模型——支持多个关键字（即OK Google和Hey Google）以及多个方言。</p>\n<p><strong>参考</strong><br>[1] <em>Wan L, Wang Q, Papir A, et al. Generalized end-to-end loss for speaker verification[C]//2018 IEEE International Conference on Acoustics, Speech and Signal Processing (ICASSP). IEEE, 2018: 4879-4883.</em><a href=\"https://arxiv.org/abs/1710.10467\">[pdf]</a></p>\n","more":"<p><strong>摘要</strong><br>本文提出了一种新型的损失函数，称为广义端到端（GE2E）损失函数，使得说话人认证模型的训练比以前基于元组的端到端（TE2E）损失函数更加有效。与TE2E不同，GE2E损失函数以强调实例的方式更新网络，这些实例在训练过程的每个步骤中都难以验证。此外，GE2E损失函数不需要选择示例的初始阶段。利用这些特性，我们的新损失函数模型使说话人验证EER降低了10%以上，同时使训练时间减少了60%。从而学习出一个更好的模型。我们还介绍了MultiReader技术，它允许我们进行域自适应训练一个更精确的模型——支持多个关键字（即OK Google和Hey Google）以及多个方言。</p>\n<p><strong>参考</strong><br>[1] <em>Wan L, Wang Q, Papir A, et al. Generalized end-to-end loss for speaker verification[C]//2018 IEEE International Conference on Acoustics, Speech and Signal Processing (ICASSP). IEEE, 2018: 4879-4883.</em><a href=\"https://arxiv.org/abs/1710.10467\">[pdf]</a></p>\n","categories":[{"name":"Paper","path":"api/categories/Paper.json"}],"tags":[{"name":"说话人认证","path":"api/tags/说话人认证.json"},{"name":"End-to-End","path":"api/tags/End-to-End.json"},{"name":"LSTM","path":"api/tags/LSTM.json"},{"name":"GE2E","path":"api/tags/GE2E.json"},{"name":"TE2E","path":"api/tags/TE2E.json"}]}